todo/__init__.py
todo/__main__.py
todo/add.py
todo/delete.py
todo/edit.py
todo/globals.py
btodo-0.0.1.dist-info/LICENSE
btodo-0.0.1.dist-info/METADATA
btodo-0.0.1.dist-info/WHEEL
btodo-0.0.1.dist-info/entry_points.txt
btodo-0.0.1.dist-info/top_level.txt
btodo-0.0.1.dist-info/RECORD
